corva_otel/utils/__init__.py
corva_otel/utils/util.py
corva_otel_utils-0.1.1.dist-info/METADATA
corva_otel_utils-0.1.1.dist-info/WHEEL
corva_otel_utils-0.1.1.dist-info/RECORD
